mkgmap/mkgmap_style.py
mkgmap/__init__.py
mkgmap/mkgmap_lex.py
mkgmap_pygments-1.5.dist-info/WHEEL
mkgmap_pygments-1.5.dist-info/RECORD
mkgmap_pygments-1.5.dist-info/METADATA
mkgmap_pygments-1.5.dist-info/DESCRIPTION.rst
mkgmap_pygments-1.5.dist-info/entry_points.txt
mkgmap_pygments-1.5.dist-info/metadata.json
mkgmap_pygments-1.5.dist-info/top_level.txt
