Metadata-Version: 2.0
Name: mkgmap-pygments
Version: 1.5
Summary: A pygments lexer and style for mkgmap style files
Home-page: https://bitbucket.org/sratcliffe/mkgmap-pygments
Author: Steve Ratcliffe
Author-email: sr@parabola.me.uk
License: GPLv3+
Keywords: mkgmap syntax highlighting
Platform: any
Classifier: Development Status :: 5 - Production/Stable
Classifier: Intended Audience :: Developers
Classifier: Intended Audience :: End Users/Desktop
Classifier: License :: OSI Approved :: GNU General Public License v3 or later (GPLv3+)
Classifier: Programming Language :: Python :: 2
Classifier: Programming Language :: Python :: 2.7
Classifier: Topic :: Text Processing :: Filters
Requires-Dist: Pygments
